music_checker_micro/__init__.py
music_checker_micro/_database.py
music_checker_micro/_file.py
music_checker_micro/_music_file.py
music_checker_micro/_mutagen_handler.py
music_checker_micro/_utils.py
music_checker_micro/music_checker.py
music_checker_micro-0.2.16.dist-info/METADATA
music_checker_micro-0.2.16.dist-info/WHEEL
music_checker_micro-0.2.16.dist-info/licenses/LICENSE
music_checker_micro-0.2.16.dist-info/RECORD
